starlette_sqlalchemy/__init__.py
starlette_sqlalchemy/collection.py
starlette_sqlalchemy/middleware.py
starlette_sqlalchemy/pagination.py
starlette_sqlalchemy/py.typed
starlette_sqlalchemy/query.py
starlette_sqlalchemy/repos.py
starlette_sqlalchemy-0.1.1.dist-info/LICENSE
starlette_sqlalchemy-0.1.1.dist-info/METADATA
starlette_sqlalchemy-0.1.1.dist-info/WHEEL
starlette_sqlalchemy-0.1.1.dist-info/RECORD
