Metadata-Version: 2.1
Name: starlette_sqlalchemy
Version: 0.1.1
Summary: SQLAlchemy integration.
Home-page: https://github.com/alex-oleshkevich/starlette_sqlalchemy
License: MIT
Author: Alex Oleshkevich
Author-email: alex.oleshkevich@gmail.com
Requires-Python: >=3.10.0,<4.0.0
Classifier: Development Status :: 5 - Production/Stable
Classifier: Environment :: Web Environment
Classifier: Intended Audience :: Developers
Classifier: License :: OSI Approved :: MIT License
Classifier: Operating System :: OS Independent
Classifier: Programming Language :: Python :: 3
Classifier: Programming Language :: Python :: 3.10
Classifier: Programming Language :: Python :: 3.11
Classifier: Programming Language :: Python :: 3.12
Classifier: Topic :: Software Development :: Libraries :: Python Modules
Classifier: Typing :: Typed
Project-URL: Documentation, https://github.com/alex-oleshkevich/starlette_sqlalchemy
Project-URL: Repository, https://github.com/alex-oleshkevich/starlette_sqlalchemy
